{"train_reward": -40.0, "train_is_success": 1.0, "timesteps_this_iter": 41, "time_this_iter_s": 68.30932307243347, "done": false, "timesteps_total": 41, "episodes_total": null, "training_iteration": 1, "experiment_id": "076cb812e376452897b1511a9c10978f", "date": "2020-11-18_22-04-51", "timestamp": 1605755091, "time_total_s": 68.30932307243347, "pid": 2104, "hostname": "scspcxxx", "node_ip": "10.32.116.100", "config": {"experiment_config": {"env_id": "KinovaReach-v0", "seed": 1, "num_resampled_goals": 4, "feature_dim": 128, "lr": 0.0006, "critic_tau": 0.005, "batch_size": 128, "hidden_sizes": [512, 512, 512], "from_images": false, "fix_goals": true}, "train_config": {"num_timesteps": 20000, "num_seed_steps": 1000, "update_after": 1000, "eval_every": 10, "gradient_steps": 1}}, "time_since_restore": 68.30932307243347, "timesteps_since_restore": 41, "iterations_since_restore": 1, "trial_id": "d45ef_00000", "experiment_tag": "0_batch_size=128,critic_tau=0.005,env_id=KinovaReach-v0,feature_dim=128,fix_goals=True,from_images=False,hidden_sizes=[512, 512, 512],lr=0.0006,num_resampled_goals=4,seed=1,eval_every=10,gradient_steps=1,num_seed_steps=1000,num_timesteps=20000,update_after=1000"}
{"train_reward": -7.0, "train_is_success": 1.0, "timesteps_this_iter": 8, "time_this_iter_s": 13.576082944869995, "done": false, "timesteps_total": 49, "episodes_total": null, "training_iteration": 2, "experiment_id": "076cb812e376452897b1511a9c10978f", "date": "2020-11-18_22-05-04", "timestamp": 1605755104, "time_total_s": 81.88540601730347, "pid": 2104, "hostname": "scspcxxx", "node_ip": "10.32.116.100", "config": {"experiment_config": {"env_id": "KinovaReach-v0", "seed": 1, "num_resampled_goals": 4, "feature_dim": 128, "lr": 0.0006, "critic_tau": 0.005, "batch_size": 128, "hidden_sizes": [512, 512, 512], "from_images": false, "fix_goals": true}, "train_config": {"num_timesteps": 20000, "num_seed_steps": 1000, "update_after": 1000, "eval_every": 10, "gradient_steps": 1}}, "time_since_restore": 81.88540601730347, "timesteps_since_restore": 49, "iterations_since_restore": 2, "trial_id": "d45ef_00000", "experiment_tag": "0_batch_size=128,critic_tau=0.005,env_id=KinovaReach-v0,feature_dim=128,fix_goals=True,from_images=False,hidden_sizes=[512, 512, 512],lr=0.0006,num_resampled_goals=4,seed=1,eval_every=10,gradient_steps=1,num_seed_steps=1000,num_timesteps=20000,update_after=1000"}
{"train_reward": -50.0, "train_is_success": 0.0, "timesteps_this_iter": 50, "time_this_iter_s": 58.2546968460083, "done": false, "timesteps_total": 99, "episodes_total": null, "training_iteration": 3, "experiment_id": "076cb812e376452897b1511a9c10978f", "date": "2020-11-18_22-06-03", "timestamp": 1605755163, "time_total_s": 140.14010286331177, "pid": 2104, "hostname": "scspcxxx", "node_ip": "10.32.116.100", "config": {"experiment_config": {"env_id": "KinovaReach-v0", "seed": 1, "num_resampled_goals": 4, "feature_dim": 128, "lr": 0.0006, "critic_tau": 0.005, "batch_size": 128, "hidden_sizes": [512, 512, 512], "from_images": false, "fix_goals": true}, "train_config": {"num_timesteps": 20000, "num_seed_steps": 1000, "update_after": 1000, "eval_every": 10, "gradient_steps": 1}}, "time_since_restore": 140.14010286331177, "timesteps_since_restore": 99, "iterations_since_restore": 3, "trial_id": "d45ef_00000", "experiment_tag": "0_batch_size=128,critic_tau=0.005,env_id=KinovaReach-v0,feature_dim=128,fix_goals=True,from_images=False,hidden_sizes=[512, 512, 512],lr=0.0006,num_resampled_goals=4,seed=1,eval_every=10,gradient_steps=1,num_seed_steps=1000,num_timesteps=20000,update_after=1000"}
{"train_reward": -50.0, "train_is_success": 0.0, "timesteps_this_iter": 50, "time_this_iter_s": 55.354482889175415, "done": false, "timesteps_total": 149, "episodes_total": null, "training_iteration": 4, "experiment_id": "076cb812e376452897b1511a9c10978f", "date": "2020-11-18_22-06-58", "timestamp": 1605755218, "time_total_s": 195.49458575248718, "pid": 2104, "hostname": "scspcxxx", "node_ip": "10.32.116.100", "config": {"experiment_config": {"env_id": "KinovaReach-v0", "seed": 1, "num_resampled_goals": 4, "feature_dim": 128, "lr": 0.0006, "critic_tau": 0.005, "batch_size": 128, "hidden_sizes": [512, 512, 512], "from_images": false, "fix_goals": true}, "train_config": {"num_timesteps": 20000, "num_seed_steps": 1000, "update_after": 1000, "eval_every": 10, "gradient_steps": 1}}, "time_since_restore": 195.49458575248718, "timesteps_since_restore": 149, "iterations_since_restore": 4, "trial_id": "d45ef_00000", "experiment_tag": "0_batch_size=128,critic_tau=0.005,env_id=KinovaReach-v0,feature_dim=128,fix_goals=True,from_images=False,hidden_sizes=[512, 512, 512],lr=0.0006,num_resampled_goals=4,seed=1,eval_every=10,gradient_steps=1,num_seed_steps=1000,num_timesteps=20000,update_after=1000"}
{"train_reward": -50.0, "train_is_success": 0.0, "timesteps_this_iter": 50, "time_this_iter_s": 59.57992506027222, "done": false, "timesteps_total": 199, "episodes_total": null, "training_iteration": 5, "experiment_id": "076cb812e376452897b1511a9c10978f", "date": "2020-11-18_22-07-58", "timestamp": 1605755278, "time_total_s": 255.0745108127594, "pid": 2104, "hostname": "scspcxxx", "node_ip": "10.32.116.100", "config": {"experiment_config": {"env_id": "KinovaReach-v0", "seed": 1, "num_resampled_goals": 4, "feature_dim": 128, "lr": 0.0006, "critic_tau": 0.005, "batch_size": 128, "hidden_sizes": [512, 512, 512], "from_images": false, "fix_goals": true}, "train_config": {"num_timesteps": 20000, "num_seed_steps": 1000, "update_after": 1000, "eval_every": 10, "gradient_steps": 1}}, "time_since_restore": 255.0745108127594, "timesteps_since_restore": 199, "iterations_since_restore": 5, "trial_id": "d45ef_00000", "experiment_tag": "0_batch_size=128,critic_tau=0.005,env_id=KinovaReach-v0,feature_dim=128,fix_goals=True,from_images=False,hidden_sizes=[512, 512, 512],lr=0.0006,num_resampled_goals=4,seed=1,eval_every=10,gradient_steps=1,num_seed_steps=1000,num_timesteps=20000,update_after=1000"}
{"train_reward": -50.0, "train_is_success": 0.0, "timesteps_this_iter": 50, "time_this_iter_s": 54.55432152748108, "done": false, "timesteps_total": 249, "episodes_total": null, "training_iteration": 6, "experiment_id": "076cb812e376452897b1511a9c10978f", "date": "2020-11-18_22-08-52", "timestamp": 1605755332, "time_total_s": 309.6288323402405, "pid": 2104, "hostname": "scspcxxx", "node_ip": "10.32.116.100", "config": {"experiment_config": {"env_id": "KinovaReach-v0", "seed": 1, "num_resampled_goals": 4, "feature_dim": 128, "lr": 0.0006, "critic_tau": 0.005, "batch_size": 128, "hidden_sizes": [512, 512, 512], "from_images": false, "fix_goals": true}, "train_config": {"num_timesteps": 20000, "num_seed_steps": 1000, "update_after": 1000, "eval_every": 10, "gradient_steps": 1}}, "time_since_restore": 309.6288323402405, "timesteps_since_restore": 249, "iterations_since_restore": 6, "trial_id": "d45ef_00000", "experiment_tag": "0_batch_size=128,critic_tau=0.005,env_id=KinovaReach-v0,feature_dim=128,fix_goals=True,from_images=False,hidden_sizes=[512, 512, 512],lr=0.0006,num_resampled_goals=4,seed=1,eval_every=10,gradient_steps=1,num_seed_steps=1000,num_timesteps=20000,update_after=1000"}
{"train_reward": -50.0, "train_is_success": 0.0, "timesteps_this_iter": 50, "time_this_iter_s": 60.004918575286865, "done": false, "timesteps_total": 299, "episodes_total": null, "training_iteration": 7, "experiment_id": "076cb812e376452897b1511a9c10978f", "date": "2020-11-18_22-09-52", "timestamp": 1605755392, "time_total_s": 369.63375091552734, "pid": 2104, "hostname": "scspcxxx", "node_ip": "10.32.116.100", "config": {"experiment_config": {"env_id": "KinovaReach-v0", "seed": 1, "num_resampled_goals": 4, "feature_dim": 128, "lr": 0.0006, "critic_tau": 0.005, "batch_size": 128, "hidden_sizes": [512, 512, 512], "from_images": false, "fix_goals": true}, "train_config": {"num_timesteps": 20000, "num_seed_steps": 1000, "update_after": 1000, "eval_every": 10, "gradient_steps": 1}}, "time_since_restore": 369.63375091552734, "timesteps_since_restore": 299, "iterations_since_restore": 7, "trial_id": "d45ef_00000", "experiment_tag": "0_batch_size=128,critic_tau=0.005,env_id=KinovaReach-v0,feature_dim=128,fix_goals=True,from_images=False,hidden_sizes=[512, 512, 512],lr=0.0006,num_resampled_goals=4,seed=1,eval_every=10,gradient_steps=1,num_seed_steps=1000,num_timesteps=20000,update_after=1000"}
{"train_reward": -6.0, "train_is_success": 1.0, "timesteps_this_iter": 7, "time_this_iter_s": 12.326026439666748, "done": false, "timesteps_total": 306, "episodes_total": null, "training_iteration": 8, "experiment_id": "076cb812e376452897b1511a9c10978f", "date": "2020-11-18_22-10-04", "timestamp": 1605755404, "time_total_s": 381.9597773551941, "pid": 2104, "hostname": "scspcxxx", "node_ip": "10.32.116.100", "config": {"experiment_config": {"env_id": "KinovaReach-v0", "seed": 1, "num_resampled_goals": 4, "feature_dim": 128, "lr": 0.0006, "critic_tau": 0.005, "batch_size": 128, "hidden_sizes": [512, 512, 512], "from_images": false, "fix_goals": true}, "train_config": {"num_timesteps": 20000, "num_seed_steps": 1000, "update_after": 1000, "eval_every": 10, "gradient_steps": 1}}, "time_since_restore": 381.9597773551941, "timesteps_since_restore": 306, "iterations_since_restore": 8, "trial_id": "d45ef_00000", "experiment_tag": "0_batch_size=128,critic_tau=0.005,env_id=KinovaReach-v0,feature_dim=128,fix_goals=True,from_images=False,hidden_sizes=[512, 512, 512],lr=0.0006,num_resampled_goals=4,seed=1,eval_every=10,gradient_steps=1,num_seed_steps=1000,num_timesteps=20000,update_after=1000"}
{"train_reward": -50.0, "train_is_success": 0.0, "timesteps_this_iter": 50, "time_this_iter_s": 56.60469627380371, "done": false, "timesteps_total": 356, "episodes_total": null, "training_iteration": 9, "experiment_id": "076cb812e376452897b1511a9c10978f", "date": "2020-11-18_22-11-01", "timestamp": 1605755461, "time_total_s": 438.5644736289978, "pid": 2104, "hostname": "scspcxxx", "node_ip": "10.32.116.100", "config": {"experiment_config": {"env_id": "KinovaReach-v0", "seed": 1, "num_resampled_goals": 4, "feature_dim": 128, "lr": 0.0006, "critic_tau": 0.005, "batch_size": 128, "hidden_sizes": [512, 512, 512], "from_images": false, "fix_goals": true}, "train_config": {"num_timesteps": 20000, "num_seed_steps": 1000, "update_after": 1000, "eval_every": 10, "gradient_steps": 1}}, "time_since_restore": 438.5644736289978, "timesteps_since_restore": 356, "iterations_since_restore": 9, "trial_id": "d45ef_00000", "experiment_tag": "0_batch_size=128,critic_tau=0.005,env_id=KinovaReach-v0,feature_dim=128,fix_goals=True,from_images=False,hidden_sizes=[512, 512, 512],lr=0.0006,num_resampled_goals=4,seed=1,eval_every=10,gradient_steps=1,num_seed_steps=1000,num_timesteps=20000,update_after=1000"}
{"train_reward": -50.0, "train_is_success": 0.0, "timesteps_this_iter": 50, "time_this_iter_s": 57.52979636192322, "done": false, "timesteps_total": 406, "episodes_total": null, "training_iteration": 10, "experiment_id": "076cb812e376452897b1511a9c10978f", "date": "2020-11-18_22-11-59", "timestamp": 1605755519, "time_total_s": 496.094269990921, "pid": 2104, "hostname": "scspcxxx", "node_ip": "10.32.116.100", "config": {"experiment_config": {"env_id": "KinovaReach-v0", "seed": 1, "num_resampled_goals": 4, "feature_dim": 128, "lr": 0.0006, "critic_tau": 0.005, "batch_size": 128, "hidden_sizes": [512, 512, 512], "from_images": false, "fix_goals": true}, "train_config": {"num_timesteps": 20000, "num_seed_steps": 1000, "update_after": 1000, "eval_every": 10, "gradient_steps": 1}}, "time_since_restore": 496.094269990921, "timesteps_since_restore": 406, "iterations_since_restore": 10, "trial_id": "d45ef_00000", "experiment_tag": "0_batch_size=128,critic_tau=0.005,env_id=KinovaReach-v0,feature_dim=128,fix_goals=True,from_images=False,hidden_sizes=[512, 512, 512],lr=0.0006,num_resampled_goals=4,seed=1,eval_every=10,gradient_steps=1,num_seed_steps=1000,num_timesteps=20000,update_after=1000"}
{"train_reward": -50.0, "train_is_success": 0.0, "timesteps_this_iter": 50, "time_this_iter_s": 59.32940316200256, "done": false, "timesteps_total": 456, "episodes_total": null, "training_iteration": 11, "experiment_id": "076cb812e376452897b1511a9c10978f", "date": "2020-11-18_22-12-58", "timestamp": 1605755578, "time_total_s": 555.4236731529236, "pid": 2104, "hostname": "scspcxxx", "node_ip": "10.32.116.100", "config": {"experiment_config": {"env_id": "KinovaReach-v0", "seed": 1, "num_resampled_goals": 4, "feature_dim": 128, "lr": 0.0006, "critic_tau": 0.005, "batch_size": 128, "hidden_sizes": [512, 512, 512], "from_images": false, "fix_goals": true}, "train_config": {"num_timesteps": 20000, "num_seed_steps": 1000, "update_after": 1000, "eval_every": 10, "gradient_steps": 1}}, "time_since_restore": 555.4236731529236, "timesteps_since_restore": 456, "iterations_since_restore": 11, "trial_id": "d45ef_00000", "experiment_tag": "0_batch_size=128,critic_tau=0.005,env_id=KinovaReach-v0,feature_dim=128,fix_goals=True,from_images=False,hidden_sizes=[512, 512, 512],lr=0.0006,num_resampled_goals=4,seed=1,eval_every=10,gradient_steps=1,num_seed_steps=1000,num_timesteps=20000,update_after=1000"}
{"train_reward": -50.0, "train_is_success": 0.0, "timesteps_this_iter": 50, "time_this_iter_s": 58.1796612739563, "done": false, "timesteps_total": 506, "episodes_total": null, "training_iteration": 12, "experiment_id": "076cb812e376452897b1511a9c10978f", "date": "2020-11-18_22-13-56", "timestamp": 1605755636, "time_total_s": 613.6033344268799, "pid": 2104, "hostname": "scspcxxx", "node_ip": "10.32.116.100", "config": {"experiment_config": {"env_id": "KinovaReach-v0", "seed": 1, "num_resampled_goals": 4, "feature_dim": 128, "lr": 0.0006, "critic_tau": 0.005, "batch_size": 128, "hidden_sizes": [512, 512, 512], "from_images": false, "fix_goals": true}, "train_config": {"num_timesteps": 20000, "num_seed_steps": 1000, "update_after": 1000, "eval_every": 10, "gradient_steps": 1}}, "time_since_restore": 613.6033344268799, "timesteps_since_restore": 506, "iterations_since_restore": 12, "trial_id": "d45ef_00000", "experiment_tag": "0_batch_size=128,critic_tau=0.005,env_id=KinovaReach-v0,feature_dim=128,fix_goals=True,from_images=False,hidden_sizes=[512, 512, 512],lr=0.0006,num_resampled_goals=4,seed=1,eval_every=10,gradient_steps=1,num_seed_steps=1000,num_timesteps=20000,update_after=1000"}
{"train_reward": -50.0, "train_is_success": 0.0, "timesteps_this_iter": 50, "time_this_iter_s": 59.404860973358154, "done": false, "timesteps_total": 556, "episodes_total": null, "training_iteration": 13, "experiment_id": "076cb812e376452897b1511a9c10978f", "date": "2020-11-18_22-14-56", "timestamp": 1605755696, "time_total_s": 673.008195400238, "pid": 2104, "hostname": "scspcxxx", "node_ip": "10.32.116.100", "config": {"experiment_config": {"env_id": "KinovaReach-v0", "seed": 1, "num_resampled_goals": 4, "feature_dim": 128, "lr": 0.0006, "critic_tau": 0.005, "batch_size": 128, "hidden_sizes": [512, 512, 512], "from_images": false, "fix_goals": true}, "train_config": {"num_timesteps": 20000, "num_seed_steps": 1000, "update_after": 1000, "eval_every": 10, "gradient_steps": 1}}, "time_since_restore": 673.008195400238, "timesteps_since_restore": 556, "iterations_since_restore": 13, "trial_id": "d45ef_00000", "experiment_tag": "0_batch_size=128,critic_tau=0.005,env_id=KinovaReach-v0,feature_dim=128,fix_goals=True,from_images=False,hidden_sizes=[512, 512, 512],lr=0.0006,num_resampled_goals=4,seed=1,eval_every=10,gradient_steps=1,num_seed_steps=1000,num_timesteps=20000,update_after=1000"}
{"train_reward": -50.0, "train_is_success": 0.0, "timesteps_this_iter": 50, "time_this_iter_s": 58.504645109176636, "done": false, "timesteps_total": 606, "episodes_total": null, "training_iteration": 14, "experiment_id": "076cb812e376452897b1511a9c10978f", "date": "2020-11-18_22-15-54", "timestamp": 1605755754, "time_total_s": 731.5128405094147, "pid": 2104, "hostname": "scspcxxx", "node_ip": "10.32.116.100", "config": {"experiment_config": {"env_id": "KinovaReach-v0", "seed": 1, "num_resampled_goals": 4, "feature_dim": 128, "lr": 0.0006, "critic_tau": 0.005, "batch_size": 128, "hidden_sizes": [512, 512, 512], "from_images": false, "fix_goals": true}, "train_config": {"num_timesteps": 20000, "num_seed_steps": 1000, "update_after": 1000, "eval_every": 10, "gradient_steps": 1}}, "time_since_restore": 731.5128405094147, "timesteps_since_restore": 606, "iterations_since_restore": 14, "trial_id": "d45ef_00000", "experiment_tag": "0_batch_size=128,critic_tau=0.005,env_id=KinovaReach-v0,feature_dim=128,fix_goals=True,from_images=False,hidden_sizes=[512, 512, 512],lr=0.0006,num_resampled_goals=4,seed=1,eval_every=10,gradient_steps=1,num_seed_steps=1000,num_timesteps=20000,update_after=1000"}
{"train_reward": -50.0, "train_is_success": 0.0, "timesteps_this_iter": 50, "time_this_iter_s": 59.529919385910034, "done": false, "timesteps_total": 656, "episodes_total": null, "training_iteration": 15, "experiment_id": "076cb812e376452897b1511a9c10978f", "date": "2020-11-18_22-16-54", "timestamp": 1605755814, "time_total_s": 791.0427598953247, "pid": 2104, "hostname": "scspcxxx", "node_ip": "10.32.116.100", "config": {"experiment_config": {"env_id": "KinovaReach-v0", "seed": 1, "num_resampled_goals": 4, "feature_dim": 128, "lr": 0.0006, "critic_tau": 0.005, "batch_size": 128, "hidden_sizes": [512, 512, 512], "from_images": false, "fix_goals": true}, "train_config": {"num_timesteps": 20000, "num_seed_steps": 1000, "update_after": 1000, "eval_every": 10, "gradient_steps": 1}}, "time_since_restore": 791.0427598953247, "timesteps_since_restore": 656, "iterations_since_restore": 15, "trial_id": "d45ef_00000", "experiment_tag": "0_batch_size=128,critic_tau=0.005,env_id=KinovaReach-v0,feature_dim=128,fix_goals=True,from_images=False,hidden_sizes=[512, 512, 512],lr=0.0006,num_resampled_goals=4,seed=1,eval_every=10,gradient_steps=1,num_seed_steps=1000,num_timesteps=20000,update_after=1000"}
{"train_reward": -50.0, "train_is_success": 0.0, "timesteps_this_iter": 50, "time_this_iter_s": 60.18002438545227, "done": false, "timesteps_total": 706, "episodes_total": null, "training_iteration": 16, "experiment_id": "076cb812e376452897b1511a9c10978f", "date": "2020-11-18_22-17-54", "timestamp": 1605755874, "time_total_s": 851.222784280777, "pid": 2104, "hostname": "scspcxxx", "node_ip": "10.32.116.100", "config": {"experiment_config": {"env_id": "KinovaReach-v0", "seed": 1, "num_resampled_goals": 4, "feature_dim": 128, "lr": 0.0006, "critic_tau": 0.005, "batch_size": 128, "hidden_sizes": [512, 512, 512], "from_images": false, "fix_goals": true}, "train_config": {"num_timesteps": 20000, "num_seed_steps": 1000, "update_after": 1000, "eval_every": 10, "gradient_steps": 1}}, "time_since_restore": 851.222784280777, "timesteps_since_restore": 706, "iterations_since_restore": 16, "trial_id": "d45ef_00000", "experiment_tag": "0_batch_size=128,critic_tau=0.005,env_id=KinovaReach-v0,feature_dim=128,fix_goals=True,from_images=False,hidden_sizes=[512, 512, 512],lr=0.0006,num_resampled_goals=4,seed=1,eval_every=10,gradient_steps=1,num_seed_steps=1000,num_timesteps=20000,update_after=1000"}
{"train_reward": -50.0, "train_is_success": 0.0, "timesteps_this_iter": 50, "time_this_iter_s": 57.254361629486084, "done": false, "timesteps_total": 756, "episodes_total": null, "training_iteration": 17, "experiment_id": "076cb812e376452897b1511a9c10978f", "date": "2020-11-18_22-18-51", "timestamp": 1605755931, "time_total_s": 908.4771459102631, "pid": 2104, "hostname": "scspcxxx", "node_ip": "10.32.116.100", "config": {"experiment_config": {"env_id": "KinovaReach-v0", "seed": 1, "num_resampled_goals": 4, "feature_dim": 128, "lr": 0.0006, "critic_tau": 0.005, "batch_size": 128, "hidden_sizes": [512, 512, 512], "from_images": false, "fix_goals": true}, "train_config": {"num_timesteps": 20000, "num_seed_steps": 1000, "update_after": 1000, "eval_every": 10, "gradient_steps": 1}}, "time_since_restore": 908.4771459102631, "timesteps_since_restore": 756, "iterations_since_restore": 17, "trial_id": "d45ef_00000", "experiment_tag": "0_batch_size=128,critic_tau=0.005,env_id=KinovaReach-v0,feature_dim=128,fix_goals=True,from_images=False,hidden_sizes=[512, 512, 512],lr=0.0006,num_resampled_goals=4,seed=1,eval_every=10,gradient_steps=1,num_seed_steps=1000,num_timesteps=20000,update_after=1000"}
{"train_reward": -50.0, "train_is_success": 0.0, "timesteps_this_iter": 50, "time_this_iter_s": 57.22956943511963, "done": false, "timesteps_total": 806, "episodes_total": null, "training_iteration": 18, "experiment_id": "076cb812e376452897b1511a9c10978f", "date": "2020-11-18_22-19-48", "timestamp": 1605755988, "time_total_s": 965.7067153453827, "pid": 2104, "hostname": "scspcxxx", "node_ip": "10.32.116.100", "config": {"experiment_config": {"env_id": "KinovaReach-v0", "seed": 1, "num_resampled_goals": 4, "feature_dim": 128, "lr": 0.0006, "critic_tau": 0.005, "batch_size": 128, "hidden_sizes": [512, 512, 512], "from_images": false, "fix_goals": true}, "train_config": {"num_timesteps": 20000, "num_seed_steps": 1000, "update_after": 1000, "eval_every": 10, "gradient_steps": 1}}, "time_since_restore": 965.7067153453827, "timesteps_since_restore": 806, "iterations_since_restore": 18, "trial_id": "d45ef_00000", "experiment_tag": "0_batch_size=128,critic_tau=0.005,env_id=KinovaReach-v0,feature_dim=128,fix_goals=True,from_images=False,hidden_sizes=[512, 512, 512],lr=0.0006,num_resampled_goals=4,seed=1,eval_every=10,gradient_steps=1,num_seed_steps=1000,num_timesteps=20000,update_after=1000"}
{"train_reward": -50.0, "train_is_success": 0.0, "timesteps_this_iter": 50, "time_this_iter_s": 59.67986249923706, "done": false, "timesteps_total": 856, "episodes_total": null, "training_iteration": 19, "experiment_id": "076cb812e376452897b1511a9c10978f", "date": "2020-11-18_22-20-48", "timestamp": 1605756048, "time_total_s": 1025.3865778446198, "pid": 2104, "hostname": "scspcxxx", "node_ip": "10.32.116.100", "config": {"experiment_config": {"env_id": "KinovaReach-v0", "seed": 1, "num_resampled_goals": 4, "feature_dim": 128, "lr": 0.0006, "critic_tau": 0.005, "batch_size": 128, "hidden_sizes": [512, 512, 512], "from_images": false, "fix_goals": true}, "train_config": {"num_timesteps": 20000, "num_seed_steps": 1000, "update_after": 1000, "eval_every": 10, "gradient_steps": 1}}, "time_since_restore": 1025.3865778446198, "timesteps_since_restore": 856, "iterations_since_restore": 19, "trial_id": "d45ef_00000", "experiment_tag": "0_batch_size=128,critic_tau=0.005,env_id=KinovaReach-v0,feature_dim=128,fix_goals=True,from_images=False,hidden_sizes=[512, 512, 512],lr=0.0006,num_resampled_goals=4,seed=1,eval_every=10,gradient_steps=1,num_seed_steps=1000,num_timesteps=20000,update_after=1000"}
{"train_reward": -50.0, "train_is_success": 0.0, "timesteps_this_iter": 50, "time_this_iter_s": 60.679776191711426, "done": false, "timesteps_total": 906, "episodes_total": null, "training_iteration": 20, "experiment_id": "076cb812e376452897b1511a9c10978f", "date": "2020-11-18_22-21-49", "timestamp": 1605756109, "time_total_s": 1086.0663540363312, "pid": 2104, "hostname": "scspcxxx", "node_ip": "10.32.116.100", "config": {"experiment_config": {"env_id": "KinovaReach-v0", "seed": 1, "num_resampled_goals": 4, "feature_dim": 128, "lr": 0.0006, "critic_tau": 0.005, "batch_size": 128, "hidden_sizes": [512, 512, 512], "from_images": false, "fix_goals": true}, "train_config": {"num_timesteps": 20000, "num_seed_steps": 1000, "update_after": 1000, "eval_every": 10, "gradient_steps": 1}}, "time_since_restore": 1086.0663540363312, "timesteps_since_restore": 906, "iterations_since_restore": 20, "trial_id": "d45ef_00000", "experiment_tag": "0_batch_size=128,critic_tau=0.005,env_id=KinovaReach-v0,feature_dim=128,fix_goals=True,from_images=False,hidden_sizes=[512, 512, 512],lr=0.0006,num_resampled_goals=4,seed=1,eval_every=10,gradient_steps=1,num_seed_steps=1000,num_timesteps=20000,update_after=1000"}
{"train_reward": -50.0, "train_is_success": 0.0, "timesteps_this_iter": 50, "time_this_iter_s": 56.704669713974, "done": false, "timesteps_total": 956, "episodes_total": null, "training_iteration": 21, "experiment_id": "076cb812e376452897b1511a9c10978f", "date": "2020-11-18_22-22-45", "timestamp": 1605756165, "time_total_s": 1142.7710237503052, "pid": 2104, "hostname": "scspcxxx", "node_ip": "10.32.116.100", "config": {"experiment_config": {"env_id": "KinovaReach-v0", "seed": 1, "num_resampled_goals": 4, "feature_dim": 128, "lr": 0.0006, "critic_tau": 0.005, "batch_size": 128, "hidden_sizes": [512, 512, 512], "from_images": false, "fix_goals": true}, "train_config": {"num_timesteps": 20000, "num_seed_steps": 1000, "update_after": 1000, "eval_every": 10, "gradient_steps": 1}}, "time_since_restore": 1142.7710237503052, "timesteps_since_restore": 956, "iterations_since_restore": 21, "trial_id": "d45ef_00000", "experiment_tag": "0_batch_size=128,critic_tau=0.005,env_id=KinovaReach-v0,feature_dim=128,fix_goals=True,from_images=False,hidden_sizes=[512, 512, 512],lr=0.0006,num_resampled_goals=4,seed=1,eval_every=10,gradient_steps=1,num_seed_steps=1000,num_timesteps=20000,update_after=1000"}
{"train_reward": -50.0, "train_is_success": 0.0, "timesteps_this_iter": 50, "critic_loss": 0.4344688057899475, "actor_loss": 0.8528200387954712, "entropy": 1.643571138381958, "alpha_loss": 0.4653456211090088, "alpha": 0.10020146689578222, "actor_Q": -1.0175271034240723, "time_this_iter_s": 55.85125184059143, "done": false, "timesteps_total": 1006, "episodes_total": null, "training_iteration": 22, "experiment_id": "076cb812e376452897b1511a9c10978f", "date": "2020-11-18_22-23-41", "timestamp": 1605756221, "time_total_s": 1198.6222755908966, "pid": 2104, "hostname": "scspcxxx", "node_ip": "10.32.116.100", "config": {"experiment_config": {"env_id": "KinovaReach-v0", "seed": 1, "num_resampled_goals": 4, "feature_dim": 128, "lr": 0.0006, "critic_tau": 0.005, "batch_size": 128, "hidden_sizes": [512, 512, 512], "from_images": false, "fix_goals": true}, "train_config": {"num_timesteps": 20000, "num_seed_steps": 1000, "update_after": 1000, "eval_every": 10, "gradient_steps": 1}}, "time_since_restore": 1198.6222755908966, "timesteps_since_restore": 1006, "iterations_since_restore": 22, "trial_id": "d45ef_00000", "experiment_tag": "0_batch_size=128,critic_tau=0.005,env_id=KinovaReach-v0,feature_dim=128,fix_goals=True,from_images=False,hidden_sizes=[512, 512, 512],lr=0.0006,num_resampled_goals=4,seed=1,eval_every=10,gradient_steps=1,num_seed_steps=1000,num_timesteps=20000,update_after=1000"}
{"train_reward": -50.0, "train_is_success": 0.0, "timesteps_this_iter": 50, "critic_loss": 0.24298837780952454, "actor_loss": 0.5953789949417114, "entropy": 1.8787707090377808, "alpha_loss": 0.4752221405506134, "alpha": 0.0973454989552472, "actor_Q": -0.7783827781677246, "time_this_iter_s": 53.82897353172302, "done": false, "timesteps_total": 1056, "episodes_total": null, "training_iteration": 23, "experiment_id": "076cb812e376452897b1511a9c10978f", "date": "2020-11-18_22-24-35", "timestamp": 1605756275, "time_total_s": 1252.4512491226196, "pid": 2104, "hostname": "scspcxxx", "node_ip": "10.32.116.100", "config": {"experiment_config": {"env_id": "KinovaReach-v0", "seed": 1, "num_resampled_goals": 4, "feature_dim": 128, "lr": 0.0006, "critic_tau": 0.005, "batch_size": 128, "hidden_sizes": [512, 512, 512], "from_images": false, "fix_goals": true}, "train_config": {"num_timesteps": 20000, "num_seed_steps": 1000, "update_after": 1000, "eval_every": 10, "gradient_steps": 1}}, "time_since_restore": 1252.4512491226196, "timesteps_since_restore": 1056, "iterations_since_restore": 23, "trial_id": "d45ef_00000", "experiment_tag": "0_batch_size=128,critic_tau=0.005,env_id=KinovaReach-v0,feature_dim=128,fix_goals=True,from_images=False,hidden_sizes=[512, 512, 512],lr=0.0006,num_resampled_goals=4,seed=1,eval_every=10,gradient_steps=1,num_seed_steps=1000,num_timesteps=20000,update_after=1000"}
{"train_reward": -50.0, "train_is_success": 0.0, "timesteps_this_iter": 50, "critic_loss": 0.3933250904083252, "actor_loss": 0.7286710739135742, "entropy": 1.8229924440383911, "alpha_loss": 0.45563480257987976, "alpha": 0.09441460093713216, "actor_Q": -0.9008916020393372, "time_this_iter_s": 54.17743539810181, "done": false, "timesteps_total": 1106, "episodes_total": null, "training_iteration": 24, "experiment_id": "076cb812e376452897b1511a9c10978f", "date": "2020-11-18_22-25-29", "timestamp": 1605756329, "time_total_s": 1306.6286845207214, "pid": 2104, "hostname": "scspcxxx", "node_ip": "10.32.116.100", "config": {"experiment_config": {"env_id": "KinovaReach-v0", "seed": 1, "num_resampled_goals": 4, "feature_dim": 128, "lr": 0.0006, "critic_tau": 0.005, "batch_size": 128, "hidden_sizes": [512, 512, 512], "from_images": false, "fix_goals": true}, "train_config": {"num_timesteps": 20000, "num_seed_steps": 1000, "update_after": 1000, "eval_every": 10, "gradient_steps": 1}}, "time_since_restore": 1306.6286845207214, "timesteps_since_restore": 1106, "iterations_since_restore": 24, "trial_id": "d45ef_00000", "experiment_tag": "0_batch_size=128,critic_tau=0.005,env_id=KinovaReach-v0,feature_dim=128,fix_goals=True,from_images=False,hidden_sizes=[512, 512, 512],lr=0.0006,num_resampled_goals=4,seed=1,eval_every=10,gradient_steps=1,num_seed_steps=1000,num_timesteps=20000,update_after=1000"}
{"train_reward": -50.0, "train_is_success": 0.0, "timesteps_this_iter": 50, "critic_loss": 0.35492974519729614, "actor_loss": 0.8764209747314453, "entropy": 1.8134187459945679, "alpha_loss": 0.44138917326927185, "alpha": 0.0916459066969337, "actor_Q": -1.0427109003067017, "time_this_iter_s": 54.83019518852234, "done": false, "timesteps_total": 1156, "episodes_total": null, "training_iteration": 25, "experiment_id": "076cb812e376452897b1511a9c10978f", "date": "2020-11-18_22-26-24", "timestamp": 1605756384, "time_total_s": 1361.4588797092438, "pid": 2104, "hostname": "scspcxxx", "node_ip": "10.32.116.100", "config": {"experiment_config": {"env_id": "KinovaReach-v0", "seed": 1, "num_resampled_goals": 4, "feature_dim": 128, "lr": 0.0006, "critic_tau": 0.005, "batch_size": 128, "hidden_sizes": [512, 512, 512], "from_images": false, "fix_goals": true}, "train_config": {"num_timesteps": 20000, "num_seed_steps": 1000, "update_after": 1000, "eval_every": 10, "gradient_steps": 1}}, "time_since_restore": 1361.4588797092438, "timesteps_since_restore": 1156, "iterations_since_restore": 25, "trial_id": "d45ef_00000", "experiment_tag": "0_batch_size=128,critic_tau=0.005,env_id=KinovaReach-v0,feature_dim=128,fix_goals=True,from_images=False,hidden_sizes=[512, 512, 512],lr=0.0006,num_resampled_goals=4,seed=1,eval_every=10,gradient_steps=1,num_seed_steps=1000,num_timesteps=20000,update_after=1000"}
{"train_reward": -8.0, "train_is_success": 1.0, "timesteps_this_iter": 9, "critic_loss": 0.3775244951248169, "actor_loss": 0.8563565015792847, "entropy": 1.7990596294403076, "alpha_loss": 0.4377913177013397, "alpha": 0.09117238635747217, "actor_Q": -1.0204746723175049, "time_this_iter_s": 14.777547597885132, "done": false, "timesteps_total": 1165, "episodes_total": null, "training_iteration": 26, "experiment_id": "076cb812e376452897b1511a9c10978f", "date": "2020-11-18_22-26-39", "timestamp": 1605756399, "time_total_s": 1376.236427307129, "pid": 2104, "hostname": "scspcxxx", "node_ip": "10.32.116.100", "config": {"experiment_config": {"env_id": "KinovaReach-v0", "seed": 1, "num_resampled_goals": 4, "feature_dim": 128, "lr": 0.0006, "critic_tau": 0.005, "batch_size": 128, "hidden_sizes": [512, 512, 512], "from_images": false, "fix_goals": true}, "train_config": {"num_timesteps": 20000, "num_seed_steps": 1000, "update_after": 1000, "eval_every": 10, "gradient_steps": 1}}, "time_since_restore": 1376.236427307129, "timesteps_since_restore": 1165, "iterations_since_restore": 26, "trial_id": "d45ef_00000", "experiment_tag": "0_batch_size=128,critic_tau=0.005,env_id=KinovaReach-v0,feature_dim=128,fix_goals=True,from_images=False,hidden_sizes=[512, 512, 512],lr=0.0006,num_resampled_goals=4,seed=1,eval_every=10,gradient_steps=1,num_seed_steps=1000,num_timesteps=20000,update_after=1000"}
{"train_reward": -50.0, "train_is_success": 0.0, "timesteps_this_iter": 50, "critic_loss": 0.2934310734272003, "actor_loss": 0.9783623218536377, "entropy": 1.748355746269226, "alpha_loss": 0.4209991693496704, "alpha": 0.08861223954874013, "actor_Q": -1.1333751678466797, "time_this_iter_s": 56.75607132911682, "done": false, "timesteps_total": 1215, "episodes_total": null, "training_iteration": 27, "experiment_id": "076cb812e376452897b1511a9c10978f", "date": "2020-11-18_22-27-36", "timestamp": 1605756456, "time_total_s": 1432.9924986362457, "pid": 2104, "hostname": "scspcxxx", "node_ip": "10.32.116.100", "config": {"experiment_config": {"env_id": "KinovaReach-v0", "seed": 1, "num_resampled_goals": 4, "feature_dim": 128, "lr": 0.0006, "critic_tau": 0.005, "batch_size": 128, "hidden_sizes": [512, 512, 512], "from_images": false, "fix_goals": true}, "train_config": {"num_timesteps": 20000, "num_seed_steps": 1000, "update_after": 1000, "eval_every": 10, "gradient_steps": 1}}, "time_since_restore": 1432.9924986362457, "timesteps_since_restore": 1215, "iterations_since_restore": 27, "trial_id": "d45ef_00000", "experiment_tag": "0_batch_size=128,critic_tau=0.005,env_id=KinovaReach-v0,feature_dim=128,fix_goals=True,from_images=False,hidden_sizes=[512, 512, 512],lr=0.0006,num_resampled_goals=4,seed=1,eval_every=10,gradient_steps=1,num_seed_steps=1000,num_timesteps=20000,update_after=1000"}
{"train_reward": -50.0, "train_is_success": 0.0, "timesteps_this_iter": 50, "critic_loss": 0.3542112410068512, "actor_loss": 1.0053719282150269, "entropy": 1.4893264770507812, "alpha_loss": 0.38726189732551575, "alpha": 0.08621801339711448, "actor_Q": -1.1338454484939575, "time_this_iter_s": 56.95102262496948, "done": false, "timesteps_total": 1265, "episodes_total": null, "training_iteration": 28, "experiment_id": "076cb812e376452897b1511a9c10978f", "date": "2020-11-18_22-28-32", "timestamp": 1605756512, "time_total_s": 1489.9435212612152, "pid": 2104, "hostname": "scspcxxx", "node_ip": "10.32.116.100", "config": {"experiment_config": {"env_id": "KinovaReach-v0", "seed": 1, "num_resampled_goals": 4, "feature_dim": 128, "lr": 0.0006, "critic_tau": 0.005, "batch_size": 128, "hidden_sizes": [512, 512, 512], "from_images": false, "fix_goals": true}, "train_config": {"num_timesteps": 20000, "num_seed_steps": 1000, "update_after": 1000, "eval_every": 10, "gradient_steps": 1}}, "time_since_restore": 1489.9435212612152, "timesteps_since_restore": 1265, "iterations_since_restore": 28, "trial_id": "d45ef_00000", "experiment_tag": "0_batch_size=128,critic_tau=0.005,env_id=KinovaReach-v0,feature_dim=128,fix_goals=True,from_images=False,hidden_sizes=[512, 512, 512],lr=0.0006,num_resampled_goals=4,seed=1,eval_every=10,gradient_steps=1,num_seed_steps=1000,num_timesteps=20000,update_after=1000"}
{"train_reward": -50.0, "train_is_success": 0.0, "timesteps_this_iter": 50, "critic_loss": 0.3082490861415863, "actor_loss": 1.1414977312088013, "entropy": 1.432960867881775, "alpha_loss": 0.37211912870407104, "alpha": 0.08389726175631099, "actor_Q": -1.2617857456207275, "time_this_iter_s": 58.331371784210205, "done": false, "timesteps_total": 1315, "episodes_total": null, "training_iteration": 29, "experiment_id": "076cb812e376452897b1511a9c10978f", "date": "2020-11-18_22-29-31", "timestamp": 1605756571, "time_total_s": 1548.2748930454254, "pid": 2104, "hostname": "scspcxxx", "node_ip": "10.32.116.100", "config": {"experiment_config": {"env_id": "KinovaReach-v0", "seed": 1, "num_resampled_goals": 4, "feature_dim": 128, "lr": 0.0006, "critic_tau": 0.005, "batch_size": 128, "hidden_sizes": [512, 512, 512], "from_images": false, "fix_goals": true}, "train_config": {"num_timesteps": 20000, "num_seed_steps": 1000, "update_after": 1000, "eval_every": 10, "gradient_steps": 1}}, "time_since_restore": 1548.2748930454254, "timesteps_since_restore": 1315, "iterations_since_restore": 29, "trial_id": "d45ef_00000", "experiment_tag": "0_batch_size=128,critic_tau=0.005,env_id=KinovaReach-v0,feature_dim=128,fix_goals=True,from_images=False,hidden_sizes=[512, 512, 512],lr=0.0006,num_resampled_goals=4,seed=1,eval_every=10,gradient_steps=1,num_seed_steps=1000,num_timesteps=20000,update_after=1000"}
{"train_reward": -5.0, "train_is_success": 1.0, "timesteps_this_iter": 6, "critic_loss": 0.32305026054382324, "actor_loss": 1.2024357318878174, "entropy": 1.4938921928405762, "alpha_loss": 0.37599456310272217, "alpha": 0.08362251667649456, "actor_Q": -1.3274264335632324, "time_this_iter_s": 11.978990316390991, "done": false, "timesteps_total": 1321, "episodes_total": null, "training_iteration": 30, "experiment_id": "076cb812e376452897b1511a9c10978f", "date": "2020-11-18_22-29-43", "timestamp": 1605756583, "time_total_s": 1560.2538833618164, "pid": 2104, "hostname": "scspcxxx", "node_ip": "10.32.116.100", "config": {"experiment_config": {"env_id": "KinovaReach-v0", "seed": 1, "num_resampled_goals": 4, "feature_dim": 128, "lr": 0.0006, "critic_tau": 0.005, "batch_size": 128, "hidden_sizes": [512, 512, 512], "from_images": false, "fix_goals": true}, "train_config": {"num_timesteps": 20000, "num_seed_steps": 1000, "update_after": 1000, "eval_every": 10, "gradient_steps": 1}}, "time_since_restore": 1560.2538833618164, "timesteps_since_restore": 1321, "iterations_since_restore": 30, "trial_id": "d45ef_00000", "experiment_tag": "0_batch_size=128,critic_tau=0.005,env_id=KinovaReach-v0,feature_dim=128,fix_goals=True,from_images=False,hidden_sizes=[512, 512, 512],lr=0.0006,num_resampled_goals=4,seed=1,eval_every=10,gradient_steps=1,num_seed_steps=1000,num_timesteps=20000,update_after=1000"}
